{"trial_id": "0484", "hyperparameters": {"space": [{"class_name": "Choice", "config": {"name": "activation", "default": "relu", "conditions": [], "values": ["relu", "tanh", "sigmoid"], "ordered": false}}, {"class_name": "Int", "config": {"name": "first_units", "default": null, "conditions": [], "min_value": 1, "max_value": 150, "step": 2, "sampling": null}}, {"class_name": "Int", "config": {"name": "num_layers", "default": null, "conditions": [], "min_value": 1, "max_value": 6, "step": 1, "sampling": null}}, {"class_name": "Int", "config": {"name": "units_0", "default": null, "conditions": [], "min_value": 1, "max_value": 150, "step": 2, "sampling": null}}, {"class_name": "Int", "config": {"name": "units_1", "default": null, "conditions": [], "min_value": 1, "max_value": 150, "step": 2, "sampling": null}}, {"class_name": "Int", "config": {"name": "units_2", "default": null, "conditions": [], "min_value": 1, "max_value": 150, "step": 2, "sampling": null}}, {"class_name": "Int", "config": {"name": "units_3", "default": null, "conditions": [], "min_value": 1, "max_value": 150, "step": 2, "sampling": null}}, {"class_name": "Int", "config": {"name": "units_4", "default": null, "conditions": [], "min_value": 1, "max_value": 150, "step": 2, "sampling": null}}, {"class_name": "Int", "config": {"name": "units_5", "default": null, "conditions": [], "min_value": 1, "max_value": 150, "step": 2, "sampling": null}}], "values": {"activation": "relu", "first_units": 59, "num_layers": 1, "units_0": 97, "units_1": 65, "units_2": 25, "units_3": 95, "units_4": 97, "units_5": 41, "tuner/epochs": 34, "tuner/initial_epoch": 12, "tuner/bracket": 2, "tuner/round": 1, "tuner/trial_id": "0478"}}, "metrics": {"metrics": {"loss": {"direction": "min", "observations": [{"value": [0.5429444313049316], "step": 15}]}, "accuracy": {"direction": "max", "observations": [{"value": [0.7365884184837341], "step": 15}]}, "val_loss": {"direction": "min", "observations": [{"value": [0.5554066896438599], "step": 15}]}, "val_accuracy": {"direction": "max", "observations": [{"value": [0.7267638444900513], "step": 15}]}}}, "score": 0.7267638444900513, "best_step": 15, "status": "COMPLETED"}