{"trial_id": "0503", "hyperparameters": {"space": [{"class_name": "Choice", "config": {"name": "activation", "default": "relu", "conditions": [], "values": ["relu", "tanh", "sigmoid"], "ordered": false}}, {"class_name": "Int", "config": {"name": "first_units", "default": null, "conditions": [], "min_value": 1, "max_value": 150, "step": 2, "sampling": null}}, {"class_name": "Int", "config": {"name": "num_layers", "default": null, "conditions": [], "min_value": 1, "max_value": 6, "step": 1, "sampling": null}}, {"class_name": "Int", "config": {"name": "units_0", "default": null, "conditions": [], "min_value": 1, "max_value": 150, "step": 2, "sampling": null}}, {"class_name": "Int", "config": {"name": "units_1", "default": null, "conditions": [], "min_value": 1, "max_value": 150, "step": 2, "sampling": null}}, {"class_name": "Int", "config": {"name": "units_2", "default": null, "conditions": [], "min_value": 1, "max_value": 150, "step": 2, "sampling": null}}, {"class_name": "Int", "config": {"name": "units_3", "default": null, "conditions": [], "min_value": 1, "max_value": 150, "step": 2, "sampling": null}}, {"class_name": "Int", "config": {"name": "units_4", "default": null, "conditions": [], "min_value": 1, "max_value": 150, "step": 2, "sampling": null}}, {"class_name": "Int", "config": {"name": "units_5", "default": null, "conditions": [], "min_value": 1, "max_value": 150, "step": 2, "sampling": null}}], "values": {"activation": "sigmoid", "first_units": 87, "num_layers": 1, "units_0": 31, "units_1": 137, "units_2": 99, "units_3": 129, "units_4": 73, "units_5": 127, "tuner/epochs": 100, "tuner/initial_epoch": 0, "tuner/bracket": 0, "tuner/round": 0}}, "metrics": {"metrics": {"loss": {"direction": "min", "observations": [{"value": [0.5354244112968445], "step": 91}]}, "accuracy": {"direction": "max", "observations": [{"value": [0.739620566368103], "step": 91}]}, "val_loss": {"direction": "min", "observations": [{"value": [0.5561798810958862], "step": 91}]}, "val_accuracy": {"direction": "max", "observations": [{"value": [0.7271137237548828], "step": 91}]}}}, "score": 0.7271137237548828, "best_step": 91, "status": "COMPLETED"}